repo_formatter/__init__.py
repo_formatter/anonymizer.py
repo_formatter/config.py
repo_formatter/core.py
repo_formatter/git_utils.py
repo_formatter/main.py
repo_formatter/token_estimator.py
repo_formatter/tree.py
repo_formatter-0.2.0.dist-info/licenses/LICENSE
repo_formatter-0.2.0.dist-info/METADATA
repo_formatter-0.2.0.dist-info/WHEEL
repo_formatter-0.2.0.dist-info/entry_points.txt
repo_formatter-0.2.0.dist-info/top_level.txt
repo_formatter-0.2.0.dist-info/RECORD
