Metadata-Version: 2.4
Name: repo-formatter
Version: 0.2.0
Summary: A tool to format repository content into a single Markdown file.
Author-email: Mounir Merah <mounir.mohammedimerah@gmail.com>
License: MIT License
Project-URL: Homepage, https://github.com/mmerah/repo-formatter
Project-URL: Bug Tracker, https://github.com/mmerah/repo-formatter/issues
Classifier: Programming Language :: Python :: 3
Classifier: License :: OSI Approved :: MIT License
Classifier: Operating System :: OS Independent
Classifier: Environment :: Console
Classifier: Topic :: Software Development :: Documentation
Classifier: Topic :: Text Processing
Requires-Python: >=3.8
License-File: LICENSE
Requires-Dist: PyYAML>=6.0
Requires-Dist: tiktoken>=0.4.0
Provides-Extra: dev
Requires-Dist: pytest; extra == "dev"
Requires-Dist: ruff; extra == "dev"
Requires-Dist: build; extra == "dev"
Requires-Dist: twine; extra == "dev"
Dynamic: license-file
